{
    "frameTimeCount": 18.000000715255737,
    "bones": [
        {
            "boneId": 1094,
            "frameType": 1,
            "startTime": 0,
            "frames": {
                "frames": [
                    {
                        "time": 0,
                        "quat": [
                            1.09375,
                            1.064453125,
                            -0.87744140625,
                            0.9482421875
                        ]
                    },
                    {
                        "time": 0.99609375,
                        "quat": [
                            1.18115234375,
                            1.1416015625,
                            -0.7626953125,
                            0.8486328125
                        ]
                    },
                    {
                        "time": 2.0068359375,
                        "quat": [
                            1.36376953125,
                            1.3232421875,
                            -0.3671875,
                            0.50390625
                        ]
                    },
                    {
                        "time": 0.99609375,
                        "quat": [
                            1.39404296875,
                            1.3564453125,
                            -0.24462890625,
                            0.39599609375
                        ]
                    },
                    {
                        "time": 0.99609375,
                        "quat": [
                            1.3935546875,
                            1.35205078125,
                            -0.25341796875,
                            0.40673828125
                        ]
                    },
                    {
                        "time": 3.0029296875,
                        "quat": [
                            1.31591796875,
                            1.2470703125,
                            -0.5283203125,
                            0.658203125
                        ]
                    },
                    {
                        "time": 10.0048828125,
                        "quat": [
                            1.22314453125,
                            1.1435546875,
                            -0.716796875,
                            0.82568359375
                        ]
                    }
                ],
                "lastFrameTime": 10.001953840255737
            }
        },
        {
            "boneId": 1095,
            "frameType": 1,
            "startTime": 0,
            "frames": {
                "frames": [
                    {
                        "time": 0,
                        "quat": [
                            0.20263671875,
                            -0.08447265625,
                            0.037109375,
                            1.9873046875
                        ]
                    },
                    {
                        "time": 3.0029296875,
                        "quat": [
                            0.37060546875,
                            -0.09814453125,
                            0.033203125,
                            1.96240234375
                        ]
                    },
                    {
                        "time": 7.001953125,
                        "quat": [
                            0.392578125,
                            -0.1025390625,
                            0.03173828125,
                            1.9580078125
                        ]
                    },
                    {
                        "time": 7.998046875,
                        "quat": [
                            0.32568359375,
                            -0.1005859375,
                            0.0322265625,
                            1.97021484375
                        ]
                    }
                ],
                "lastFrameTime": 7.995117902755737
            }
        },
        {
            "boneId": 1096,
            "frameType": 1,
            "startTime": 0,
            "frames": {
                "frames": [
                    {
                        "time": 0,
                        "quat": [
                            0.00927734375,
                            -0.205078125,
                            0.00439453125,
                            1.9892578125
                        ]
                    },
                    {
                        "time": 3.0029296875,
                        "quat": [
                            0.07470703125,
                            -0.27978515625,
                            -0.0234375,
                            1.978515625
                        ]
                    },
                    {
                        "time": 3.9990234375,
                        "quat": [
                            0.0791015625,
                            -0.30322265625,
                            -0.03076171875,
                            1.97509765625
                        ]
                    },
                    {
                        "time": 11.0009765625,
                        "quat": [
                            0.01416015625,
                            -0.294921875,
                            -0.021484375,
                            1.97802734375
                        ]
                    }
                ],
                "lastFrameTime": 10.998047590255737
            }
        },
        {
            "boneId": 1040,
            "frameType": 1,
            "startTime": 0,
            "frames": {
                "frames": [
                    {
                        "time": 0,
                        "quat": [
                            -0.41552734375,
                            -0.2353515625,
                            -0.0673828125,
                            1.94091796875
                        ]
                    },
                    {
                        "time": 3.9990234375,
                        "quat": [
                            -0.41943359375,
                            -0.228515625,
                            -0.099609375,
                            1.939453125
                        ]
                    },
                    {
                        "time": 14.00390625,
                        "quat": [
                            -0.4169921875,
                            -0.22119140625,
                            -0.04345703125,
                            1.94287109375
                        ]
                    }
                ],
                "lastFrameTime": 14.000977277755737
            }
        },
        {
            "boneId": 1001,
            "frameType": 1,
            "startTime": 0,
            "frames": {
                "frames": [
                    {
                        "time": 0,
                        "quat": [
                            -0.25390625,
                            -0.10107421875,
                            -0.37939453125,
                            1.9443359375
                        ]
                    },
                    {
                        "time": 0.99609375,
                        "quat": [
                            -0.33349609375,
                            0.00830078125,
                            -0.42138671875,
                            1.92626953125
                        ]
                    },
                    {
                        "time": 2.0068359375,
                        "quat": [
                            -0.49755859375,
                            0.310546875,
                            -0.447265625,
                            1.85888671875
                        ]
                    },
                    {
                        "time": 0.99609375,
                        "quat": [
                            -0.5390625,
                            0.39111328125,
                            -0.43798828125,
                            1.833984375
                        ]
                    },
                    {
                        "time": 0.99609375,
                        "quat": [
                            -0.5517578125,
                            0.38818359375,
                            -0.42041015625,
                            1.8349609375
                        ]
                    },
                    {
                        "time": 3.0029296875,
                        "quat": [
                            -0.5361328125,
                            0.25,
                            -0.353515625,
                            1.87744140625
                        ]
                    },
                    {
                        "time": 10.0048828125,
                        "quat": [
                            -0.29736328125,
                            0.3095703125,
                            -0.275390625,
                            1.93359375
                        ]
                    }
                ],
                "lastFrameTime": 10.001953840255737
            }
        },
        {
            "boneId": 3333,
            "frameType": 3,
            "startTime": 0.99609375,
            "frames": {
                "frames": [
                    {
                        "position": [
                            0.08837890625,
                            -0.01904296875,
                            0.15283203125
                        ]
                    },
                    {
                        "position": [
                            0.08837890625,
                            -0.01904296875,
                            0.15283203125
                        ]
                    },
                    {
                        "position": [
                            0.08837890625,
                            -0.01904296875,
                            0.15283203125
                        ]
                    },
                    {
                        "position": [
                            0.08837890625,
                            -0.01904296875,
                            0.15283203125
                        ]
                    },
                    {
                        "position": [
                            0.08837890625,
                            -0.01904296875,
                            0.15283203125
                        ]
                    },
                    {
                        "position": [
                            0.08837890625,
                            -0.01904296875,
                            0.15283203125
                        ]
                    },
                    {
                        "position": [
                            0.08837890625,
                            -0.01904296875,
                            0.15283203125
                        ]
                    },
                    {
                        "position": [
                            0.08837890625,
                            -0.01904296875,
                            0.15283203125
                        ]
                    },
                    {
                        "position": [
                            0.08837890625,
                            -0.01904296875,
                            0.15283203125
                        ]
                    },
                    {
                        "position": [
                            0.08837890625,
                            -0.01904296875,
                            0.15283203125
                        ]
                    },
                    {
                        "position": [
                            0.08837890625,
                            -0.01904296875,
                            0.15283203125
                        ]
                    },
                    {
                        "position": [
                            0.08837890625,
                            -0.01904296875,
                            0.15283203125
                        ]
                    },
                    {
                        "position": [
                            0.08837890625,
                            -0.01904296875,
                            0.15283203125
                        ]
                    },
                    {
                        "position": [
                            0.08837890625,
                            -0.01904296875,
                            0.15283203125
                        ]
                    },
                    {
                        "position": [
                            0.08837890625,
                            -0.01904296875,
                            0.15283203125
                        ]
                    },
                    {
                        "position": [
                            0.08837890625,
                            -0.01904296875,
                            0.15283203125
                        ]
                    },
                    {
                        "position": [
                            0.08837890625,
                            -0.01904296875,
                            0.15283203125
                        ]
                    },
                    {
                        "position": [
                            0.08837890625,
                            -0.01904296875,
                            0.15283203125
                        ]
                    },
                    {
                        "position": [
                            0.08837890625,
                            -0.01904296875,
                            0.15283203125
                        ]
                    }
                ],
                "lastFrameTime": 1.0664069652557373
            },
            "direction": [
                0.07958984375,
                -0.0791015625,
                1.412109375,
                1.412109375
            ]
        },
        {
            "boneId": 1003,
            "frameType": 2,
            "startTime": 0.99609375,
            "frames": {
                "frames": [
                    {
                        "quat": [
                            1.63916015625,
                            0.9677734375,
                            0.31201171875,
                            0.52734375
                        ],
                        "position": [
                            0.1318359375,
                            0.04541015625,
                            0.00146484375
                        ]
                    },
                    {
                        "quat": [
                            1.6259765625,
                            0.9931640625,
                            0.3173828125,
                            0.5185546875
                        ],
                        "position": [
                            0.1318359375,
                            0.04541015625,
                            0.00146484375
                        ]
                    },
                    {
                        "quat": [
                            1.61865234375,
                            1.0771484375,
                            0.26025390625,
                            0.3896484375
                        ],
                        "position": [
                            0.1318359375,
                            0.04541015625,
                            0.00146484375
                        ]
                    },
                    {
                        "quat": [
                            1.5986328125,
                            1.158203125,
                            0.18798828125,
                            0.25830078125
                        ],
                        "position": [
                            0.1318359375,
                            0.04541015625,
                            0.00146484375
                        ]
                    },
                    {
                        "quat": [
                            1.56689453125,
                            1.22998046875,
                            0.10986328125,
                            0.138671875
                        ],
                        "position": [
                            0.1318359375,
                            0.04541015625,
                            0.00146484375
                        ]
                    },
                    {
                        "quat": [
                            1.6337890625,
                            1.14794921875,
                            0.06640625,
                            0.09326171875
                        ],
                        "position": [
                            0.1318359375,
                            0.04541015625,
                            0.00146484375
                        ]
                    },
                    {
                        "quat": [
                            1.6708984375,
                            1.0966796875,
                            0.0390625,
                            0.05810546875
                        ],
                        "position": [
                            0.1318359375,
                            0.04541015625,
                            0.00146484375
                        ]
                    },
                    {
                        "quat": [
                            1.6591796875,
                            1.115234375,
                            0.0341796875,
                            0.04931640625
                        ],
                        "position": [
                            0.1318359375,
                            0.04541015625,
                            0.00146484375
                        ]
                    },
                    {
                        "quat": [
                            1.63134765625,
                            1.1552734375,
                            0.03564453125,
                            0.048828125
                        ],
                        "position": [
                            0.1318359375,
                            0.04541015625,
                            0.00146484375
                        ]
                    },
                    {
                        "quat": [
                            1.5966796875,
                            1.20263671875,
                            0.04150390625,
                            0.0537109375
                        ],
                        "position": [
                            0.1318359375,
                            0.04541015625,
                            0.00146484375
                        ]
                    },
                    {
                        "quat": [
                            1.56591796875,
                            1.24169921875,
                            0.0498046875,
                            0.06103515625
                        ],
                        "position": [
                            0.1318359375,
                            0.04541015625,
                            0.00146484375
                        ]
                    },
                    {
                        "quat": [
                            1.541015625,
                            1.271484375,
                            0.05859375,
                            0.06982421875
                        ],
                        "position": [
                            0.1318359375,
                            0.04541015625,
                            0.00146484375
                        ]
                    },
                    {
                        "quat": [
                            1.51611328125,
                            1.2998046875,
                            0.0693359375,
                            0.07958984375
                        ],
                        "position": [
                            0.1318359375,
                            0.04541015625,
                            0.00146484375
                        ]
                    },
                    {
                        "quat": [
                            1.4912109375,
                            1.3271484375,
                            0.08154296875,
                            0.09033203125
                        ],
                        "position": [
                            0.1318359375,
                            0.04541015625,
                            0.00146484375
                        ]
                    },
                    {
                        "quat": [
                            1.46630859375,
                            1.35302734375,
                            0.09423828125,
                            0.10107421875
                        ],
                        "position": [
                            0.1318359375,
                            0.04541015625,
                            0.00146484375
                        ]
                    },
                    {
                        "quat": [
                            1.44091796875,
                            1.37841796875,
                            0.1083984375,
                            0.11181640625
                        ],
                        "position": [
                            0.1318359375,
                            0.04541015625,
                            0.00146484375
                        ]
                    },
                    {
                        "quat": [
                            1.4150390625,
                            1.40283203125,
                            0.12255859375,
                            0.12255859375
                        ],
                        "position": [
                            0.1318359375,
                            0.04541015625,
                            0.00146484375
                        ]
                    },
                    {
                        "quat": [
                            1.38818359375,
                            1.42724609375,
                            0.13720703125,
                            0.13232421875
                        ],
                        "position": [
                            0.1318359375,
                            0.04541015625,
                            0.00146484375
                        ]
                    },
                    {
                        "quat": [
                            1.36083984375,
                            1.45068359375,
                            0.1513671875,
                            0.14111328125
                        ],
                        "position": [
                            0.1318359375,
                            0.04541015625,
                            0.00146484375
                        ]
                    }
                ],
                "lastFrameTime": 1.0664069652557373
            }
        },
        {
            "boneId": 1039,
            "frameType": 1,
            "startTime": 0,
            "frames": {
                "frames": [
                    {
                        "time": 0,
                        "quat": [
                            0.125,
                            0.345703125,
                            0.19677734375,
                            1.9560546875
                        ]
                    },
                    {
                        "time": 0.99609375,
                        "quat": [
                            0.19921875,
                            0.31103515625,
                            0.22412109375,
                            1.95263671875
                        ]
                    },
                    {
                        "time": 2.0068359375,
                        "quat": [
                            0.546875,
                            0.32421875,
                            0.21435546875,
                            1.88427734375
                        ]
                    },
                    {
                        "time": 0.99609375,
                        "quat": [
                            0.6708984375,
                            -0.041015625,
                            0.298828125,
                            1.85986328125
                        ]
                    },
                    {
                        "time": 0.99609375,
                        "quat": [
                            0.70166015625,
                            0.14208984375,
                            0.33984375,
                            1.83642578125
                        ]
                    },
                    {
                        "time": 1.0107421875,
                        "quat": [
                            0.724609375,
                            0.25439453125,
                            0.39453125,
                            1.80419921875
                        ]
                    },
                    {
                        "time": 0.99609375,
                        "quat": [
                            0.72802734375,
                            0.21728515625,
                            0.49560546875,
                            1.78271484375
                        ]
                    },
                    {
                        "time": 1.9921875,
                        "quat": [
                            0.70458984375,
                            0.03857421875,
                            0.72021484375,
                            1.7275390625
                        ]
                    },
                    {
                        "time": 1.0107421875,
                        "quat": [
                            0.68798828125,
                            0.0029296875,
                            0.7880859375,
                            1.70458984375
                        ]
                    },
                    {
                        "time": 2.98828125,
                        "quat": [
                            0.63037109375,
                            0.0966796875,
                            0.86572265625,
                            1.6865234375
                        ]
                    },
                    {
                        "time": 5.009765625,
                        "quat": [
                            0.48388671875,
                            0.333984375,
                            0.90185546875,
                            1.685546875
                        ]
                    }
                ],
                "lastFrameTime": 5.006836652755737
            }
        },
        {
            "boneId": 1020,
            "frameType": 1,
            "startTime": 0,
            "frames": {
                "frames": [
                    {
                        "time": 0,
                        "quat": [
                            0,
                            1.833984375,
                            0,
                            0.7978515625
                        ]
                    },
                    {
                        "time": 0.99609375,
                        "quat": [
                            0,
                            1.4921875,
                            0,
                            1.33154296875
                        ]
                    },
                    {
                        "time": 1.0107421875,
                        "quat": [
                            0,
                            0.77197265625,
                            0,
                            1.84521484375
                        ]
                    },
                    {
                        "time": 0.99609375,
                        "quat": [
                            0,
                            0.04150390625,
                            0,
                            1.99951171875
                        ]
                    },
                    {
                        "time": 0.99609375,
                        "quat": [
                            0,
                            0.12744140625,
                            0,
                            1.99609375
                        ]
                    },
                    {
                        "time": 2.0068359375,
                        "quat": [
                            0,
                            0.623046875,
                            0,
                            1.900390625
                        ]
                    },
                    {
                        "time": 0.99609375,
                        "quat": [
                            0,
                            1.0107421875,
                            0,
                            1.7255859375
                        ]
                    },
                    {
                        "time": 0.99609375,
                        "quat": [
                            0,
                            1.4013671875,
                            0,
                            1.4267578125
                        ]
                    },
                    {
                        "time": 0.99609375,
                        "quat": [
                            0,
                            1.67431640625,
                            0,
                            1.09423828125
                        ]
                    },
                    {
                        "time": 1.0107421875,
                        "quat": [
                            0,
                            1.79345703125,
                            0,
                            0.88525390625
                        ]
                    },
                    {
                        "time": 0.99609375,
                        "quat": [
                            0,
                            1.822265625,
                            0,
                            0.82421875
                        ]
                    },
                    {
                        "time": 1.9921875,
                        "quat": [
                            0,
                            1.8095703125,
                            0,
                            0.85205078125
                        ]
                    },
                    {
                        "time": 5.009765625,
                        "quat": [
                            0,
                            1.60400390625,
                            0,
                            1.19482421875
                        ]
                    }
                ],
                "lastFrameTime": 5.006836652755737
            }
        },
        {
            "boneId": 1021,
            "frameType": 1,
            "startTime": 0,
            "frames": {
                "frames": [
                    {
                        "time": 0,
                        "quat": [
                            1.607421875,
                            0.28173828125,
                            0.302734375,
                            1.1162109375
                        ]
                    },
                    {
                        "time": 0.99609375,
                        "quat": [
                            1.59716796875,
                            0.2275390625,
                            0.32861328125,
                            1.1357421875
                        ]
                    },
                    {
                        "time": 3.0029296875,
                        "quat": [
                            1.2978515625,
                            0.0556640625,
                            0.15771484375,
                            1.51220703125
                        ]
                    },
                    {
                        "time": 4.9951171875,
                        "quat": [
                            1.27490234375,
                            0.00146484375,
                            0.0244140625,
                            1.54052734375
                        ]
                    },
                    {
                        "time": 3.9990234375,
                        "quat": [
                            1.2763671875,
                            0.07958984375,
                            0.048828125,
                            1.537109375
                        ]
                    },
                    {
                        "time": 5.009765625,
                        "quat": [
                            1.283203125,
                            0.23291015625,
                            0.1455078125,
                            1.50927734375
                        ]
                    }
                ],
                "lastFrameTime": 5.006836652755737
            }
        },
        {
            "boneId": 1057,
            "frameType": 2,
            "startTime": 0.99609375,
            "frames": {
                "frames": [
                    {
                        "quat": [
                            1.408203125,
                            -1.396484375,
                            -0.17919921875,
                            0.18212890625
                        ],
                        "position": [
                            0.1318359375,
                            -0.044921875,
                            0.00146484375
                        ]
                    },
                    {
                        "quat": [
                            -1.37353515625,
                            1.42626953125,
                            0.2001953125,
                            -0.193359375
                        ],
                        "position": [
                            0.1318359375,
                            -0.044921875,
                            0.00146484375
                        ]
                    },
                    {
                        "quat": [
                            -1.34619140625,
                            1.44873046875,
                            0.216796875,
                            -0.2021484375
                        ],
                        "position": [
                            0.1318359375,
                            -0.044921875,
                            0.00146484375
                        ]
                    },
                    {
                        "quat": [
                            -1.3271484375,
                            1.46337890625,
                            0.228515625,
                            -0.20751953125
                        ],
                        "position": [
                            0.1318359375,
                            -0.044921875,
                            0.00146484375
                        ]
                    },
                    {
                        "quat": [
                            -1.31982421875,
                            1.46923828125,
                            0.23291015625,
                            -0.2099609375
                        ],
                        "position": [
                            0.1318359375,
                            -0.044921875,
                            0.00146484375
                        ]
                    },
                    {
                        "quat": [
                            -1.3212890625,
                            1.46826171875,
                            0.23193359375,
                            -0.20947265625
                        ],
                        "position": [
                            0.1318359375,
                            -0.044921875,
                            0.00146484375
                        ]
                    },
                    {
                        "quat": [
                            -1.328125,
                            1.462890625,
                            0.2275390625,
                            -0.20751953125
                        ],
                        "position": [
                            0.1318359375,
                            -0.044921875,
                            0.00146484375
                        ]
                    },
                    {
                        "quat": [
                            -1.337890625,
                            1.455078125,
                            0.2216796875,
                            -0.20458984375
                        ],
                        "position": [
                            0.1318359375,
                            -0.044921875,
                            0.00146484375
                        ]
                    },
                    {
                        "quat": [
                            -1.35107421875,
                            1.44482421875,
                            0.21337890625,
                            -0.2001953125
                        ],
                        "position": [
                            0.1318359375,
                            -0.044921875,
                            0.00146484375
                        ]
                    },
                    {
                        "quat": [
                            -1.36669921875,
                            1.43212890625,
                            0.2041015625,
                            -0.1953125
                        ],
                        "position": [
                            0.1318359375,
                            -0.044921875,
                            0.00146484375
                        ]
                    },
                    {
                        "quat": [
                            -1.384765625,
                            1.4169921875,
                            0.193359375,
                            -0.189453125
                        ],
                        "position": [
                            0.1318359375,
                            -0.044921875,
                            0.00146484375
                        ]
                    },
                    {
                        "quat": [
                            1.4111328125,
                            -1.39404296875,
                            -0.17626953125,
                            0.18017578125
                        ],
                        "position": [
                            0.1318359375,
                            -0.044921875,
                            0.00146484375
                        ]
                    },
                    {
                        "quat": [
                            1.443359375,
                            -1.36474609375,
                            -0.15625,
                            0.1669921875
                        ],
                        "position": [
                            0.1318359375,
                            -0.044921875,
                            0.00146484375
                        ]
                    },
                    {
                        "quat": [
                            1.46875,
                            -1.34033203125,
                            -0.14111328125,
                            0.15625
                        ],
                        "position": [
                            0.1318359375,
                            -0.044921875,
                            0.00146484375
                        ]
                    },
                    {
                        "quat": [
                            1.4755859375,
                            -1.33349609375,
                            -0.13818359375,
                            0.154296875
                        ],
                        "position": [
                            0.1318359375,
                            -0.044921875,
                            0.00146484375
                        ]
                    },
                    {
                        "quat": [
                            1.4560546875,
                            -1.35205078125,
                            -0.15283203125,
                            0.166015625
                        ],
                        "position": [
                            0.1318359375,
                            -0.044921875,
                            0.00146484375
                        ]
                    },
                    {
                        "quat": [
                            1.41748046875,
                            -1.38623046875,
                            -0.18017578125,
                            0.185546875
                        ],
                        "position": [
                            0.1318359375,
                            -0.044921875,
                            0.00146484375
                        ]
                    },
                    {
                        "quat": [
                            -1.3701171875,
                            1.42578125,
                            0.2138671875,
                            -0.20654296875
                        ],
                        "position": [
                            0.1318359375,
                            -0.044921875,
                            0.00146484375
                        ]
                    },
                    {
                        "quat": [
                            -1.3251953125,
                            1.4599609375,
                            0.24658203125,
                            -0.22412109375
                        ],
                        "position": [
                            0.1318359375,
                            -0.044921875,
                            0.00146484375
                        ]
                    }
                ],
                "lastFrameTime": 1.0664069652557373
            }
        },
        {
            "boneId": 1093,
            "frameType": 1,
            "startTime": 0,
            "frames": {
                "frames": [
                    {
                        "time": 0,
                        "quat": [
                            0.11279296875,
                            0.67919921875,
                            -0.892578125,
                            1.65185546875
                        ]
                    },
                    {
                        "time": 0.99609375,
                        "quat": [
                            0.21044921875,
                            0.32373046875,
                            -0.83740234375,
                            1.7744140625
                        ]
                    },
                    {
                        "time": 1.0107421875,
                        "quat": [
                            0.25390625,
                            -0.14404296875,
                            -0.72412109375,
                            1.84130859375
                        ]
                    },
                    {
                        "time": 0.99609375,
                        "quat": [
                            0.2578125,
                            -0.46142578125,
                            -0.619140625,
                            1.82666015625
                        ]
                    },
                    {
                        "time": 0.99609375,
                        "quat": [
                            0.2626953125,
                            -0.51708984375,
                            -0.58740234375,
                            1.8212890625
                        ]
                    },
                    {
                        "time": 0.99609375,
                        "quat": [
                            0.26513671875,
                            -0.4306640625,
                            -0.60009765625,
                            1.83935546875
                        ]
                    },
                    {
                        "time": 2.0068359375,
                        "quat": [
                            0.21142578125,
                            -0.15966796875,
                            -0.65966796875,
                            1.869140625
                        ]
                    },
                    {
                        "time": 3.0029296875,
                        "quat": [
                            0.04345703125,
                            0.34423828125,
                            -0.75341796875,
                            1.81982421875
                        ]
                    },
                    {
                        "time": 2.98828125,
                        "quat": [
                            0.0361328125,
                            0.7412109375,
                            -0.7578125,
                            1.6953125
                        ]
                    },
                    {
                        "time": 1.0107421875,
                        "quat": [
                            0.02587890625,
                            0.783203125,
                            -0.75439453125,
                            1.67822265625
                        ]
                    },
                    {
                        "time": 0.99609375,
                        "quat": [
                            0.0009765625,
                            0.734375,
                            -0.75732421875,
                            1.69921875
                        ]
                    },
                    {
                        "time": 3.0029296875,
                        "quat": [
                            -0.14453125,
                            0.3564453125,
                            -0.74169921875,
                            1.81689453125
                        ]
                    }
                ],
                "lastFrameTime": 3.0000007152557373
            }
        },
        {
            "boneId": 1074,
            "frameType": 1,
            "startTime": 0,
            "frames": {
                "frames": [
                    {
                        "time": 0,
                        "quat": [
                            0,
                            1.47900390625,
                            0,
                            1.34619140625
                        ]
                    },
                    {
                        "time": 0.99609375,
                        "quat": [
                            0,
                            1.60693359375,
                            0,
                            1.19091796875
                        ]
                    },
                    {
                        "time": 1.0107421875,
                        "quat": [
                            0,
                            1.7802734375,
                            0,
                            0.9111328125
                        ]
                    },
                    {
                        "time": 0.99609375,
                        "quat": [
                            0,
                            1.8818359375,
                            0,
                            0.6767578125
                        ]
                    },
                    {
                        "time": 0.99609375,
                        "quat": [
                            0,
                            1.9150390625,
                            0,
                            0.5771484375
                        ]
                    },
                    {
                        "time": 0.99609375,
                        "quat": [
                            0,
                            1.92333984375,
                            0,
                            0.5478515625
                        ]
                    },
                    {
                        "time": 2.0068359375,
                        "quat": [
                            0,
                            1.89990234375,
                            0,
                            0.62548828125
                        ]
                    },
                    {
                        "time": 3.0029296875,
                        "quat": [
                            0,
                            1.7919921875,
                            0,
                            0.888671875
                        ]
                    },
                    {
                        "time": 0.99609375,
                        "quat": [
                            0,
                            1.77587890625,
                            0,
                            0.91943359375
                        ]
                    },
                    {
                        "time": 7.001953125,
                        "quat": [
                            0,
                            1.7900390625,
                            0,
                            0.89208984375
                        ]
                    }
                ],
                "lastFrameTime": 6.999024152755737
            }
        },
        {
            "boneId": 1075,
            "frameType": 1,
            "startTime": 0,
            "frames": {
                "frames": [
                    {
                        "time": 0,
                        "quat": [
                            -1.61376953125,
                            0.17626953125,
                            -0.16943359375,
                            1.1552734375
                        ]
                    },
                    {
                        "time": 2.0068359375,
                        "quat": [
                            -1.69091796875,
                            0.12841796875,
                            -0.0927734375,
                            1.05517578125
                        ]
                    },
                    {
                        "time": 1.9921875,
                        "quat": [
                            -1.7197265625,
                            0.10791015625,
                            -0.06103515625,
                            1.01220703125
                        ]
                    },
                    {
                        "time": 3.0029296875,
                        "quat": [
                            -1.69970703125,
                            0.12255859375,
                            -0.08349609375,
                            1.04296875
                        ]
                    },
                    {
                        "time": 3.0029296875,
                        "quat": [
                            -1.6435546875,
                            0.15869140625,
                            -0.14111328125,
                            1.119140625
                        ]
                    },
                    {
                        "time": 2.98828125,
                        "quat": [
                            -1.5205078125,
                            0.2265625,
                            -0.25048828125,
                            1.25390625
                        ]
                    },
                    {
                        "time": 1.0107421875,
                        "quat": [
                            -1.51220703125,
                            0.23095703125,
                            -0.25732421875,
                            1.26220703125
                        ]
                    },
                    {
                        "time": 0.99609375,
                        "quat": [
                            -1.548828125,
                            0.212890625,
                            -0.22705078125,
                            1.22607421875
                        ]
                    },
                    {
                        "time": 3.0029296875,
                        "quat": [
                            1.73779296875,
                            -0.0966796875,
                            0.0419921875,
                            -0.98388671875
                        ]
                    }
                ],
                "lastFrameTime": 3.0000007152557373
            }
        }
    ],
    "unknown5": "00004040",
    "entry": []
}